amazon_pricepal/__init__.py
amazon_pricepal-0.1.2.dist-info/METADATA
amazon_pricepal-0.1.2.dist-info/WHEEL
amazon_pricepal-0.1.2.dist-info/top_level.txt
amazon_pricepal-0.1.2.dist-info/RECORD
