Metadata-Version: 2.4
Name: amazon_pricepal
Version: 0.1.2
Summary: A package to fetch Amazon product prices.
Author-email: David <daviddum345@gmail.com>
Requires-Python: >=3.8
Requires-Dist: requests
Requires-Dist: beautifulsoup4
